SteveChessboardSmith23/ChessBoard2000.py
SteveChessboardSmith23/__init__.py
SteveChessboardSmith23-0.0.3.dist-info/LICENSE.txt
SteveChessboardSmith23-0.0.3.dist-info/METADATA
SteveChessboardSmith23-0.0.3.dist-info/WHEEL
SteveChessboardSmith23-0.0.3.dist-info/top_level.txt
SteveChessboardSmith23-0.0.3.dist-info/RECORD
