Metadata-Version: 2.1
Name: SteveChessboardSmith23
Version: 0.0.3
Summary: It is a chess board
Home-page: https://github.com/STEVE-al/ChessBoardGame
Author: steve
Author-email: s.smith200712@gmail.com
License: UNKNOWN
Platform: UNKNOWN
Classifier: Programming Language :: Python :: 3
Classifier: License :: OSI Approved :: MIT License
Classifier: Operating System :: OS Independent
Requires-Python: >=3.6
